Metadata-Version: 2.1
Name: chill-filter
Version: 0.4.1
Summary: rapid sample screening for shotgun DNA sequencing data sets
Author: C. Titus Brown
Project-URL: Source, https://github.com/dib-lab/chill-filter
License-File: LICENSE
